tornado_user/__init__.py
tornado_user-0.0.1.dist-info/LICENSE
tornado_user-0.0.1.dist-info/METADATA
tornado_user-0.0.1.dist-info/WHEEL
tornado_user-0.0.1.dist-info/top_level.txt
tornado_user-0.0.1.dist-info/RECORD
