Metadata-Version: 2.1
Name: tornado-user
Version: 0.0.1
Summary: User accounts in Tornado applications
Home-page: https://github.com/tornadostack/tornado_user
Author: Sean Harrison
Author-email: sah@bookgenesis.com
License: UNKNOWN
Platform: UNKNOWN
Classifier: Development Status :: 1 - Planning
Classifier: Intended Audience :: Developers
Classifier: License :: OSI Approved :: Mozilla Public License 2.0 (MPL 2.0)
Classifier: Programming Language :: Python :: 3
Provides-Extra: dev
Provides-Extra: test
